CHANGES.txt
LICENSE.GPL
LICENSE.txt
MANIFEST.in
README.rst
setup.py
leocornus/__init__.py
leocornus.recipe.distribute.egg-info/PKG-INFO
leocornus.recipe.distribute.egg-info/SOURCES.txt
leocornus.recipe.distribute.egg-info/dependency_links.txt
leocornus.recipe.distribute.egg-info/entry_points.txt
leocornus.recipe.distribute.egg-info/namespace_packages.txt
leocornus.recipe.distribute.egg-info/not-zip-safe
leocornus.recipe.distribute.egg-info/requires.txt
leocornus.recipe.distribute.egg-info/top_level.txt
leocornus/recipe/__init__.py
leocornus/recipe/distribute/README.rst
leocornus/recipe/distribute/__init__.py
leocornus/recipe/distribute/utils.py
leocornus/recipe/distribute/tests/__init__.py
leocornus/recipe/distribute/tests/basicDataCompressAndArchiving.rst
leocornus/recipe/distribute/tests/basicLocalFabric.rst
leocornus/recipe/distribute/tests/testDoctests.py
leocornus/recipe/distribute/tests/versionPatternGrep.rst