Metadata-Version: 1.0
Name: leocornus.recipe.distribute
Version: 2.1.5
Summary: zc.buildout recipe for package and distribute files, modules, libs, archives, etc.
Home-page: http://github.com/leocornus/leocornus.recipe.distribute
Author: Sean Chen
Author-email: sean.chen@leocorn.com
License: GPLv2
Keywords: development buildout recipe package distribute
Platform: UNKNOWN
Classifier: Framework :: Buildout
Classifier: Intended Audience :: Developers
Classifier: License :: OSI Approved :: GNU General Public License (GPL)
Classifier: Topic :: Software Development :: Build Tools
Classifier: Topic :: Software Development :: Libraries :: Python Modules
